<annotation>
	<folder>CamThermal_vis_color</folder>
	<filename>CamThermal_001172314000.bmp</filename>
	<path>/home/asad/data3/asahmed/advanced_project_2/project/fumarole_localization/data/CamThermal_vis_color/CamThermal_001172314000.bmp</path>
	<source>
		<database>Unknown</database>
	</source>
	<size>
		<width>382</width>
		<height>288</height>
		<depth>3</depth>
	</size>
	<segmented>0</segmented>
	<object>
		<name>fumarole</name>
		<pose>Unspecified</pose>
		<truncated>0</truncated>
		<difficult>0</difficult>
		<bndbox>
			<xmin>47</xmin>
			<ymin>140</ymin>
			<xmax>83</xmax>
			<ymax>186</ymax>
		</bndbox>
	</object>
	<object>
		<name>fumarole</name>
		<pose>Unspecified</pose>
		<truncated>0</truncated>
		<difficult>0</difficult>
		<bndbox>
			<xmin>91</xmin>
			<ymin>161</ymin>
			<xmax>107</xmax>
			<ymax>188</ymax>
		</bndbox>
	</object>
	<object>
		<name>fumarole</name>
		<pose>Unspecified</pose>
		<truncated>0</truncated>
		<difficult>0</difficult>
		<bndbox>
			<xmin>82</xmin>
			<ymin>218</ymin>
			<xmax>102</xmax>
			<ymax>230</ymax>
		</bndbox>
	</object>
	<object>
		<name>fumarole</name>
		<pose>Unspecified</pose>
		<truncated>0</truncated>
		<difficult>0</difficult>
		<bndbox>
			<xmin>215</xmin>
			<ymin>166</ymin>
			<xmax>233</xmax>
			<ymax>183</ymax>
		</bndbox>
	</object>
	<object>
		<name>fumarole</name>
		<pose>Unspecified</pose>
		<truncated>0</truncated>
		<difficult>0</difficult>
		<bndbox>
			<xmin>204</xmin>
			<ymin>229</ymin>
			<xmax>219</xmax>
			<ymax>256</ymax>
		</bndbox>
	</object>
</annotation>
